{
    "shape": [
        285,
        20
    ],
    "missing_values": {
        "fecha": 0,
        "id": 1,
        "edad": 0,
        "genero": 0,
        "nivel_socioeconomico": 0,
        "grado_estudios": 0,
        "situacion_actual": 0,
        "area_trabajo": 0,
        "estado_origen": 0,
        "municipio_origen": 0,
        "pregunta_1": 0,
        "pregunta_2": 0,
        "pregunta_3": 0,
        "pregunta_4": 0,
        "pregunta_5": 0,
        "pregunta_6": 0,
        "pregunta_7": 0,
        "pregunta_8": 0,
        "pregunta_9": 0,
        "pregunta_10": 0
    },
    "demographics": {
        "edad_stats": {
            "count": 285.0,
            "mean": 21.45263157894737,
            "std": 1.9542392762912264,
            "min": 17.0,
            "25%": 20.0,
            "50%": 21.0,
            "75%": 23.0,
            "max": 29.0
        },
        "genero_dist": {
            "Masculino": 202,
            "Femenino": 78,
            "LGBT+": 5
        },
        "nivel_socioeco_dist": {
            "Medio": 218,
            "Bajo": 64,
            "Alto": 3
        },
        "education_dist": {
            "Licenciatura": 209,
            "Bachillerato": 75,
            "Maestría": 1
        }
    },
    "text_analysis": {},
    "geographic_distribution": {
        "estado_dist": {
            "Puebla": 194,
            "Tlaxcala": 30,
            "Veracruz": 25,
            "Oaxaca": 14,
            "Guerrero": 5,
            "Morelos": 4,
            "Ciudad de México": 4,
            "Tabasco": 2,
            "Chiapas": 2,
            "Hidalgo": 2,
            "Chihuahua": 1,
            "Michoacán": 1,
            "Estado de México": 1
        },
        "municipio_dist": {
            "Puebla": 77,
            "Puebla ": 39,
            "Córdoba ": 4,
            "Cuautlancingo": 3,
            "Oaxaca de Juárez ": 3,
            "Tlaxcala ": 3,
            "Zacatelco ": 2,
            "Tehuacán": 2,
            "Apizaco": 2,
            "Chilpancingo": 2,
            "Ixtacuixtla de Mariano Matamoros": 2,
            "Cuautlancingo ": 2,
            "Coronango": 2,
            "San Pedro Cholula": 2,
            "Tlapacoyan": 2,
            "San Pablo del Monte": 2,
            "PUEBLA": 2,
            "Tenancingo ": 2,
            "Tehuacán ": 2,
            "Amozoc": 2,
            "San Andrés Cholula": 2,
            "Acuamanala ": 2,
            "Tepeaca": 2,
            "Xicotepec ": 2,
            "Amozoc ": 2,
            "Zacatlán": 2,
            "Coatzacoalcos": 2,
            "Tecamachalco": 2,
            "Alvaro Obregon": 1,
            "San Antonio de la Cal": 1,
            "San Martin Texmelucan Puebla": 1,
            "salina cruz oaxaca": 1,
            "Tepoztlán ": 1,
            "San Martin Xaltocan": 1,
            "San pedro cholula": 1,
            "Coscomatepec": 1,
            "Ecatepec ": 1,
            "Coronango ": 1,
            "Santa Cruz Quilehtla": 1,
            "Atzitzintla": 1,
            "Tepetzintla": 1,
            "San Andrés Calpan Puebla ": 1,
            "Apizaco ": 1,
            "Puebla, Puebla": 1,
            "Cuautempan": 1,
            "San Pedro Cholula ": 1,
            "Atoyac de Álvarez": 1,
            "San Rafael": 1,
            "Xalapa": 1,
            "Tepexi de Rodríguez ": 1,
            "San Pablo del Monte ": 1,
            "Teziutlán ": 1,
            "Barrio de la soledad": 1,
            "Tuxtepec": 1,
            "Azcapotzalco": 1,
            "Zongozotla": 1,
            "Contla de juan cuamatzi ": 1,
            "Soltepec": 1,
            "puebla": 1,
            "Orizaba, Ver ": 1,
            "Santa María Coronango": 1,
            "Huajuapan de León": 1,
            "Tlanepantla ": 1,
            "Venustiano Carranza": 1,
            "Poza Rica ": 1,
            "Cuantlancingo": 1,
            "Tlanepantla Puebla ": 1,
            "Misantla": 1,
            "San Matías Tlalancaleca": 1,
            "Cuernavaca": 1,
            "Poza Rica": 1,
            "Pachuca de Soto": 1,
            "Sanctorum de Lázaro Cárdenas ": 1,
            "Tlacotepec de Benito Juárez ": 1,
            "Acajete": 1,
            "Nealtican ": 1,
            "Petlalcingo ": 1,
            "Ixhuatlán del Café": 1,
            "Puebla.": 1,
            "San Andrés Cholula ": 1,
            "Chilcuautla": 1,
            "Ayometla": 1,
            "Zaragoza": 1,
            "Atlixco ": 1,
            "Calpulalpan ": 1,
            "Jantetelco": 1,
            "Atlixco": 1,
            "Martinez de la Torre": 1,
            "Acapulco ": 1,
            "TUXTLA GUTIERREZ": 1,
            "Puebla de Zaragoza ": 1,
            "Texmelucan ": 1,
            "San Martín Texmelucan": 1,
            "Palmar de Bravo ": 1,
            "Huauchinango": 1,
            "Zihutanejo": 1,
            "Orizaba": 1,
            "Santa María Moyotzingo": 1,
            "Minatitlan": 1,
            "Cuernavaca ": 1,
            "Ixtaczoquitlán": 1,
            "Huejotzingo": 1,
            "Hueytamalco ": 1,
            "Calpan": 1,
            "Huamantla ": 1,
            "Villahermosa ": 1,
            "Tochtepec ": 1,
            "San Matías Tlalancaleca ": 1,
            "zacatelco ": 1,
            "San Miguel Xoxtla ": 1,
            "San Miguel Xoxtla Puebla ": 1,
            "Huajuapan de León ": 1,
            "Cd. Juarez": 1,
            "Zamora": 1,
            "San Martín Tilcajete": 1,
            "Tlanepantla": 1,
            "Juchitan de Zaragoza ": 1,
            "Totolac": 1,
            "Acultzingo ": 1,
            "La Magdalena Tlaltelulco, Tlaxcala ": 1,
            "Villahermosa": 1,
            "Izúcar de Matamoros ": 1,
            "Coatzacoalcos ": 1,
            "Momoxpan": 1,
            "Tlacotepec de Benito Juárez": 1,
            "Tuxtla Gutiérrez": 1,
            "San Martín Texmelucan ": 1,
            "Tlacolula de Matamoros": 1,
            "Nanacamilpa ": 1,
            "Puebla, Pue.": 1,
            "Huamantla": 1,
            "cuautlancingo": 1,
            "Ixhuatlan del Sureste ": 1,
            "Chocaman": 1,
            "Coscomatepec de Bravo": 1,
            "Cuitlahuac ": 1,
            "Huajuapan de Leon ": 1,
            "Zacatelco": 1,
            "San Agustín Loxicha ": 1,
            "Tochimilco": 1
        }
    },
    "occupation_analysis": {
        "status": {
            "Estudiando": 222,
            "Ambos": 54,
            "Trabajando": 6,
            "Ninguno": 3
        },
        "work_area": {
            "Estudiante - Para quienes están en instituciones educativas.": 108,
            "Otro - Para quienes no encajen en las categorías anteriores.": 57,
            "Tecnología e informática - Desarrolladores de software, técnicos de IT, analistas de sistemas, etc.": 29,
            "Desempleo - Para quienes actualmente no están trabajando.": 28,
            "Comercio y ventas - Vendedores, gerentes de tienda, representantes de atención al cliente, etc.": 20,
            "Autoempleo - Emprendedores, freelance, etc.": 17,
            "Sector administrativo y de oficina - Incluye roles como asistente administrativo, recepcionista, etc.": 8,
            "Construcción y trabajo manual - Carpinteros, electricistas, plomeros, etc.": 7,
            "Arte y diseño - Artistas, diseñadores gráficos, fotógrafos, etc.": 4,
            "Sector de la salud - Médicos, enfermeras, técnicos, terapeutas, etc.": 3,
            "Sector de la educación - Maestros, educadores, administradores educativos, etc.": 2,
            "Ingeniería y manufactura - Ingenieros, operadores de maquinaria, técnicos, etc.": 2
        }
    }
}